types_eplus221/Airconditioner_Variablerefrigerantflow.pyi
types_eplus221/Airconditioner_Variablerefrigerantflow_Fluidtemperaturecontrol.pyi
types_eplus221/Airconditioner_Variablerefrigerantflow_Fluidtemperaturecontrol_Hr.pyi
types_eplus221/Airflownetwork_Distribution_Component_Coil.pyi
types_eplus221/Airflownetwork_Distribution_Component_Constantpressuredrop.pyi
types_eplus221/Airflownetwork_Distribution_Component_Duct.pyi
types_eplus221/Airflownetwork_Distribution_Component_Fan.pyi
types_eplus221/Airflownetwork_Distribution_Component_Heatexchanger.pyi
types_eplus221/Airflownetwork_Distribution_Component_Leak.pyi
types_eplus221/Airflownetwork_Distribution_Component_Leakageratio.pyi
types_eplus221/Airflownetwork_Distribution_Component_Outdoorairflow.pyi
types_eplus221/Airflownetwork_Distribution_Component_Reliefairflow.pyi
types_eplus221/Airflownetwork_Distribution_Component_Terminalunit.pyi
types_eplus221/Airflownetwork_Distribution_Ductviewfactors.pyi
types_eplus221/Airflownetwork_Distribution_Linkage.pyi
types_eplus221/Airflownetwork_Distribution_Node.pyi
types_eplus221/Airflownetwork_Intrazone_Linkage.pyi
types_eplus221/Airflownetwork_Intrazone_Node.pyi
types_eplus221/Airflownetwork_Multizone_Component_Detailedopening.pyi
types_eplus221/Airflownetwork_Multizone_Component_Horizontalopening.pyi
types_eplus221/Airflownetwork_Multizone_Component_Simpleopening.pyi
types_eplus221/Airflownetwork_Multizone_Component_Zoneexhaustfan.pyi
types_eplus221/Airflownetwork_Multizone_Externalnode.pyi
types_eplus221/Airflownetwork_Multizone_Referencecrackconditions.pyi
types_eplus221/Airflownetwork_Multizone_Surface.pyi
types_eplus221/Airflownetwork_Multizone_Surface_Crack.pyi
types_eplus221/Airflownetwork_Multizone_Surface_Effectiveleakagearea.pyi
types_eplus221/Airflownetwork_Multizone_Windpressurecoefficientarray.pyi
types_eplus221/Airflownetwork_Multizone_Windpressurecoefficientvalues.pyi
types_eplus221/Airflownetwork_Multizone_Zone.pyi
types_eplus221-0.1.2.dist-info/WHEEL
types_eplus221-0.1.2.dist-info/METADATA
types_eplus221-0.1.2.dist-info/RECORD
