Metadata-Version: 2.3
Name: types-eplus221
Version: 0.1.2
Summary: Type stubs for EnergyPlusV22.1
Classifier: Typing :: Stubs Only
Classifier: Programming Language :: Python :: 3
Requires-Python: >=3.9
